caloutils/__init__.py
caloutils/calorimeter.py
caloutils/distances/__init__.py
caloutils/distances/ecdf.py
caloutils/distances/hist.py
caloutils/distances/scaled_w1.py
caloutils/distances/wasserstein.py
caloutils/processing/__init__.py
caloutils/processing/batch_to_Exyz.py
caloutils/processing/nhits_in_same_cell.py
caloutils/processing/pc_from_voxel.py
caloutils/processing/pc_to_voxel.py
caloutils/processing/shift_multi_hits.py
caloutils/processing/sum_multi_hits.py
caloutils/processing/utils.py
caloutils/utils/__init__.py
caloutils/utils/batch.py
caloutils/utils/scaling.py
caloutils/variables/__init__.py
caloutils/variables/analyze_layers.py
caloutils/variables/calculate_variables.py
caloutils/variables/energy_ratios.py
caloutils/variables/first_principal_components.py
caloutils/variables/response.py
caloutils-0.0.18.dist-info/LICENSE
caloutils-0.0.18.dist-info/WHEEL
caloutils-0.0.18.dist-info/METADATA
caloutils-0.0.18.dist-info/RECORD
