Metadata-Version: 2.1
Name: caloutils
Version: 0.0.18
Summary: Metrics and tools for evaluation generative models for calorimeter shower based on pytorch_geometric.
Author-email: mova <mova@users.noreply.github.com>, kaechb <kaechb@users.noreply.github.com>
Requires-Python: >=3.8
Classifier: Programming Language :: Python :: 3
Classifier: License :: OSI Approved :: MIT License
Classifier: Operating System :: OS Independent
Requires-Dist: torch>=2.0.0
Requires-Dist: torch_geometric>=2.3.0
Requires-Dist: torch-scatter>=2.1.1
Requires-Dist: pytest >=2.7.3 ; extra == "dev"
Requires-Dist: pytest-cov ; extra == "dev"
Requires-Dist: bump2version ; extra == "dev"
Requires-Dist: black ; extra == "dev"
Requires-Dist: pre-commit ; extra == "dev"
Requires-Dist: ruff ; extra == "dev"
Requires-Dist: mock ; extra == "dev"
Requires-Dist: sphinx ; extra == "doc"
Requires-Dist: sphinx_rtd_theme ; extra == "doc"
Requires-Dist: autodocsumm ; extra == "doc"
Requires-Dist: readthedocs-sphinx-search ; extra == "doc"
Project-URL: Bug Tracker, https://github.com/DeGeSim/caloutils/issues
Project-URL: Homepage, https://github.com/DeGeSim/caloutils
Provides-Extra: dev
Provides-Extra: doc
